ticlib/__init__.py
ticlib/ticlib.py
ticlib-0.2.2.dist-info/LICENSE
ticlib-0.2.2.dist-info/METADATA
ticlib-0.2.2.dist-info/WHEEL
ticlib-0.2.2.dist-info/top_level.txt
ticlib-0.2.2.dist-info/RECORD
