Metadata-Version: 2.1
Name: ticlib
Version: 0.2.2
Summary: Python library to drive Pololu Tic stepper motor controllers
Home-page: https://github.com/jphalip/ticlib
Author: Julien Phalip
Author-email: jphalip@gmail.com
License: BSD-2-Clause
Project-URL: Bug Tracker, https://github.com/jphalip/ticlib/issues
Platform: UNKNOWN
Classifier: Programming Language :: Python :: 3
Classifier: License :: OSI Approved :: BSD License
Classifier: Operating System :: OS Independent
Requires-Python: >=3.6
